itertable/__init__.py
itertable/__main__.py
itertable/base.py
itertable/commands.py
itertable/exceptions.py
itertable/loaders.py
itertable/mappers.py
itertable/util.py
itertable/version.py
itertable/gis/__init__.py
itertable/gis/mixins.py
itertable/parsers/__init__.py
itertable/parsers/base.py
itertable/parsers/readers.py
itertable/parsers/text.py
itertable/parsers/xls.py
itertable-2.2.0.dist-info/LICENSE
itertable-2.2.0.dist-info/METADATA
itertable-2.2.0.dist-info/WHEEL
itertable-2.2.0.dist-info/top_level.txt
itertable-2.2.0.dist-info/RECORD
