Metadata-Version: 2.1
Name: itertable
Version: 2.2.0
Summary: Iterable API for tabular datasets including CSV, XLSX, XML, & JSON.
Author-email: "S. Andrew Sheppard" <andrew@wq.io>
License: MIT
Project-URL: Homepage, https://django-data-wizard.wq.io/itertable/
Project-URL: Documentation, https://django-data-wizard.wq.io/itertable/
Project-URL: Source, https://github.com/wq/itertable/
Project-URL: Release Notes, https://github.com/wq/itertable/releases
Project-URL: Issues, https://github.com/wq/itertable/issues
Project-URL: CI, https://github.com/wq/itertable/actions/workflows/test.yml
Classifier: Development Status :: 5 - Production/Stable
Classifier: License :: OSI Approved :: MIT License
Classifier: Natural Language :: English
Classifier: Programming Language :: Python :: 3
Classifier: Programming Language :: Python :: 3.7
Classifier: Programming Language :: Python :: 3.8
Classifier: Programming Language :: Python :: 3.9
Classifier: Programming Language :: Python :: 3.10
Classifier: Programming Language :: Python :: 3.11
Classifier: Intended Audience :: Science/Research
Classifier: Intended Audience :: Developers
Classifier: Topic :: Text Processing :: Markup :: XML
Classifier: Topic :: Scientific/Engineering :: GIS
Classifier: Topic :: Utilities
Requires-Python: >=3.7
Provides-Extra: gis
Provides-Extra: pandas
Provides-Extra: oldexel
License-File: LICENSE
